LICENSE
MANIFEST.in
setup.py
saucelabs/__init__.py
saucelabs/tests.py
saucelabs/selenium/__init__.py
saucelabs/selenium/selenium_test_suite.py
saucelabs/selenium/selenium_test_suite_headless.py
saucelabs/selenium/test_ajax_jsf.py
saucelabs/selenium/test_default_server.py
saucelabs/selenium/test_google.py
saucelabs/selenium/test_i18n.py
selenium_saucelabs_python.egg-info/PKG-INFO
selenium_saucelabs_python.egg-info/SOURCES.txt
selenium_saucelabs_python.egg-info/dependency_links.txt
selenium_saucelabs_python.egg-info/not-zip-safe
selenium_saucelabs_python.egg-info/requires.txt
selenium_saucelabs_python.egg-info/top_level.txt