Metadata-Version: 1.0
Name: selenium-saucelabs-python
Version: 0.3.1
Summary: Sauce OnDemand driver for Python
Home-page: http://github.com/dcramer/selenium-saucelabs-python
Author: David Cramer
Author-email: dcramer@gmail.com
License: UNKNOWN
Platform: UNKNOWN
Classifier: Framework :: Django
Classifier: Intended Audience :: Developers
Classifier: Intended Audience :: System Administrators
Classifier: Operating System :: OS Independent
Classifier: Topic :: Software Development
